address_formatter/__init__.py
address_formatter/async_api.py
address_formatter/cli.py
address_formatter/compat.py
address_formatter/config.py
address_formatter/formatter.py
address_formatter/optimizations.py
address_formatter/types.py
address_formatter/api/__init__.py
address_formatter/api/main.py
address_formatter/api/middleware.py
address_formatter/api/server.py
address_formatter/cache/__init__.py
address_formatter/cache/cache_manager.py
address_formatter/cache/utils.py
address_formatter/core/__init__.py
address_formatter/core/abbreviations.py
address_formatter/core/country_rules.py
address_formatter/core/formatter.py
address_formatter/core/normalizer.py
address_formatter/core/renderer.py
address_formatter/core/template_loader.py
address_formatter/data/__init__.py
address_formatter/data/templates/abbreviations.json
address_formatter/data/templates/aliases.json
address_formatter/data/templates/countries.json
address_formatter/data/templates/worldwide.json
address_formatter/events/__init__.py
address_formatter/events/bus.py
address_formatter/events/types.py
address_formatter/management/__init__.py
address_formatter/management/prepare_templates.py
address_formatter/management/process_templates.py
address_formatter/monitoring/__init__.py
address_formatter/monitoring/metrics.py
address_formatter/plugins/__init__.py
address_formatter/plugins/interface.py
address_formatter/plugins/manager.py
address_formatter/plugins/builtins/__init__.py
address_formatter/plugins/builtins/abbreviation_plugin.py
address_formatter/plugins/builtins/add_country_plugin.py
address_formatter/plugins/builtins/ml_integration_plugin.py
address_formatter/plugins/builtins/output_format_plugin.py
ml/__init__.py
ml/predictor.py
ml/trainer.py
pyaddress/__init__.py
py_address_formatter-0.1.2.dist-info/METADATA
py_address_formatter-0.1.2.dist-info/WHEEL
py_address_formatter-0.1.2.dist-info/entry_points.txt
py_address_formatter-0.1.2.dist-info/top_level.txt
py_address_formatter-0.1.2.dist-info/RECORD
