Metadata-Version: 2.4
Name: py-address-formatter
Version: 0.1.2
Summary: Python library for formatting addresses according to country-specific rules
Home-page: https://github.com/address-formatter/pyaddress
Author: Solchos
Author-email: solchos@gmail.com
Classifier: Development Status :: 4 - Beta
Classifier: Intended Audience :: Developers
Classifier: License :: OSI Approved :: MIT License
Classifier: Programming Language :: Python :: 3
Classifier: Programming Language :: Python :: 3.8
Classifier: Programming Language :: Python :: 3.9
Classifier: Programming Language :: Python :: 3.10
Classifier: Topic :: Software Development :: Libraries :: Python Modules
Classifier: Topic :: Text Processing :: Linguistic
Requires-Python: >=3.8
Requires-Dist: pyyaml>=6.0
Requires-Dist: chevron>=0.14.0
Requires-Dist: python-slugify>=8.0.0
Requires-Dist: fastapi>=0.68.0
Requires-Dist: pydantic>=1.8.0
Requires-Dist: pydantic-settings>=2.0.0
Requires-Dist: uvicorn>=0.15.0
Requires-Dist: prometheus-client>=0.13.0
Requires-Dist: click>=8.1.0
Provides-Extra: api
Requires-Dist: fastapi>=0.68.0; extra == "api"
Requires-Dist: uvicorn>=0.15.0; extra == "api"
Requires-Dist: prometheus-client>=0.13.0; extra == "api"
Provides-Extra: async
Requires-Dist: aiofiles>=0.8.0; extra == "async"
Requires-Dist: asyncio>=3.4.3; extra == "async"
Requires-Dist: httpx>=0.22.0; extra == "async"
Provides-Extra: ml
Requires-Dist: spacy>=3.4.0; extra == "ml"
Requires-Dist: sentence-transformers>=2.2.0; extra == "ml"
Requires-Dist: networkx>=2.8.0; extra == "ml"
Provides-Extra: optimize
Requires-Dist: numba>=0.56.0; platform_machine != "arm64" and extra == "optimize"
Provides-Extra: dev
Requires-Dist: pytest>=6.0.0; extra == "dev"
Requires-Dist: pytest-cov>=2.12.0; extra == "dev"
Requires-Dist: mypy>=0.910; extra == "dev"
Requires-Dist: hypothesis>=6.0.0; extra == "dev"
Requires-Dist: black>=21.5b2; extra == "dev"
Requires-Dist: isort>=5.9.0; extra == "dev"
Dynamic: author
Dynamic: author-email
Dynamic: classifier
Dynamic: description
Dynamic: description-content-type
Dynamic: home-page
Dynamic: provides-extra
Dynamic: requires-dist
Dynamic: requires-python
Dynamic: summary
